__init__.py
core.py
gopyhash-1.0.1.dist-info/licenses/LICENSE
gopyhash-1.0.1.dist-info/METADATA
gopyhash-1.0.1.dist-info/WHEEL
gopyhash-1.0.1.dist-info/top_level.txt
gopyhash-1.0.1.dist-info/RECORD
