Metadata-Version: 2.4
Name: gopyhash
Version: 1.0.1
Summary: A package for password hashing and comparision using bcrypt
Author-email: Humaun Kabir <hello@ihumaun.com>
License: MIT
Project-URL: Homepage, https://github.com/ihumaunkabir/gopyhash
Project-URL: Bug Tracker, https://github.com/ihumaunkabir/gopyhash/issues
Keywords: bcrypt,security,password,text,hashing
Classifier: Programming Language :: Python :: 3.10
Classifier: License :: OSI Approved :: MIT License
Classifier: Operating System :: OS Independent
Classifier: Intended Audience :: Developers
Classifier: Topic :: Security :: Cryptography
Requires-Python: >=3.10
License-File: LICENSE
Requires-Dist: bcrypt>=4.0.0
Dynamic: license-file
